alterpy/__init__.py
alterpy/alias_dict.py
alterpy/exception.py
alterpy-1.0.0.dist-info/LICENSE
alterpy-1.0.0.dist-info/METADATA
alterpy-1.0.0.dist-info/WHEEL
alterpy-1.0.0.dist-info/top_level.txt
alterpy-1.0.0.dist-info/RECORD
