Metadata-Version: 2.1
Name: alterpy
Version: 1.0.0
Summary: Multi-key dictionary, supports adding and manipulating key-aliases pointing to shared values
Author-email: Kaloyan Ivanov <kaloyan.ivanov88@gmail.com>
Project-URL: repository, https://github.com/kaliv0/alterpy
Keywords: multi-key dictionary,multidict,alias-dict
Requires-Python: >=3.11
License-File: LICENSE
Provides-Extra: dev
Requires-Dist: pytest>=8.3.4; extra == "dev"
Requires-Dist: ruff>=0.8.3; extra == "dev"
Requires-Dist: build>=1.2.2; extra == "dev"
Requires-Dist: twine>=6.0.1; extra == "dev"
